[
    {
      "inputs": [
        {
          "internalType": "address",
          "name": "_router",
          "type": "address"
        },
        {
          "internalType": "address",
          "name": "_factory",
          "type": "address"
        },
        {
          "internalType": "address",
          "name": "_WETH",
          "type": "address"
        }
      ],
      "stateMutability": "nonpayable",
      "type": "constructor"
    },
    {
      "inputs": [],
      "name": "WETH",
      "outputs": [
        {
          "internalType": "contract IWETH9",
          "name": "",
          "type": "address"
        }
      ],
      "stateMutability": "view",
      "type": "function"
    },
    {
      "inputs": [
        {
          "components": [
            {
              "internalType": "uint256",
              "name": "amountIn",
              "type": "uint256"
            },
            {
              "internalType": "uint256",
              "name": "reserveIn",
              "type": "uint256"
            },
            {
              "internalType": "uint256",
              "name": "reserveOut",
              "type": "uint256"
            }
          ],
          "internalType": "struct IOptimalSwap.GetAmountOutParams",
          "name": "params",
          "type": "tuple"
        }
      ],
      "name": "getAmountOut",
      "outputs": [
        {
          "internalType": "uint256",
          "name": "",
          "type": "uint256"
        }
      ],
      "stateMutability": "pure",
      "type": "function"
    },
    {
      "inputs": [
        {
          "components": [
            {
              "internalType": "address",
              "name": "_fromToken",
              "type": "address"
            },
            {
              "internalType": "address",
              "name": "_toToken",
              "type": "address"
            },
            {
              "internalType": "uint256",
              "name": "amountDesired",
              "type": "uint256"
            }
          ],
          "internalType": "struct IOptimalSwap.GetExpectedAmountsParams",
          "name": "params",
          "type": "tuple"
        }
      ],
      "name": "getExpectedAmounts",
      "outputs": [
        {
          "components": [
            {
              "internalType": "uint256",
              "name": "fromTokenAmount",
              "type": "uint256"
            },
            {
              "internalType": "uint256",
              "name": "toTokenAmount",
              "type": "uint256"
            },
            {
              "internalType": "uint256",
              "name": "fromTokenRest",
              "type": "uint256"
            },
            {
              "internalType": "uint256",
              "name": "toTokenRest",
              "type": "uint256"
            }
          ],
          "internalType": "struct IOptimalSwap.GetExpectedAmountsReturn",
          "name": "returnVal",
          "type": "tuple"
        }
      ],
      "stateMutability": "view",
      "type": "function"
    },
    {
      "inputs": [
        {
          "components": [
            {
              "internalType": "address",
              "name": "fromToken",
              "type": "address"
            },
            {
              "internalType": "address",
              "name": "toToken",
              "type": "address"
            },
            {
              "internalType": "uint256",
              "name": "amountInputDesired",
              "type": "uint256"
            },
            {
              "internalType": "uint256",
              "name": "swapAmountOutMin",
              "type": "uint256"
            },
            {
              "internalType": "uint256",
              "name": "slippage",
              "type": "uint256"
            },
            {
              "internalType": "address",
              "name": "to",
              "type": "address"
            },
            {
              "internalType": "uint256",
              "name": "deadline",
              "type": "uint256"
            }
          ],
          "internalType": "struct IOptimalSwap.SwapAndAddLiquidityParams",
          "name": "params",
          "type": "tuple"
        }
      ],
      "name": "swapAndAddLiquidity",
      "outputs": [
        {
          "internalType": "uint256",
          "name": "amountA",
          "type": "uint256"
        },
        {
          "internalType": "uint256",
          "name": "amountB",
          "type": "uint256"
        },
        {
          "internalType": "uint256",
          "name": "liquidity",
          "type": "uint256"
        }
      ],
      "stateMutability": "nonpayable",
      "type": "function"
    },
    {
      "inputs": [
        {
          "components": [
            {
              "internalType": "address",
              "name": "toToken",
              "type": "address"
            },
            {
              "internalType": "uint256",
              "name": "swapAmountOutMin",
              "type": "uint256"
            },
            {
              "internalType": "uint256",
              "name": "slippage",
              "type": "uint256"
            },
            {
              "internalType": "address",
              "name": "to",
              "type": "address"
            },
            {
              "internalType": "uint256",
              "name": "deadline",
              "type": "uint256"
            }
          ],
          "internalType": "struct IOptimalSwap.SwapAndAddLiquidityParamsFromETH",
          "name": "params",
          "type": "tuple"
        }
      ],
      "name": "swapAndAddLiquidityFromETH",
      "outputs": [
        {
          "internalType": "uint256",
          "name": "amountA",
          "type": "uint256"
        },
        {
          "internalType": "uint256",
          "name": "amountB",
          "type": "uint256"
        },
        {
          "internalType": "uint256",
          "name": "liquidity",
          "type": "uint256"
        }
      ],
      "stateMutability": "payable",
      "type": "function"
    },
    {
      "inputs": [
        {
          "components": [
            {
              "internalType": "address",
              "name": "fromToken",
              "type": "address"
            },
            {
              "internalType": "uint256",
              "name": "amountInputDesired",
              "type": "uint256"
            },
            {
              "internalType": "uint256",
              "name": "swapAmountOutMin",
              "type": "uint256"
            },
            {
              "internalType": "uint256",
              "name": "slippage",
              "type": "uint256"
            },
            {
              "internalType": "address",
              "name": "to",
              "type": "address"
            },
            {
              "internalType": "uint256",
              "name": "deadline",
              "type": "uint256"
            }
          ],
          "internalType": "struct IOptimalSwap.SwapAndAddLiquidityParamsToETH",
          "name": "params",
          "type": "tuple"
        }
      ],
      "name": "swapAndAddLiquidityToETH",
      "outputs": [
        {
          "internalType": "uint256",
          "name": "amountA",
          "type": "uint256"
        },
        {
          "internalType": "uint256",
          "name": "amountB",
          "type": "uint256"
        },
        {
          "internalType": "uint256",
          "name": "liquidity",
          "type": "uint256"
        }
      ],
      "stateMutability": "nonpayable",
      "type": "function"
    },
    {
      "inputs": [],
      "name": "uniswapFactory",
      "outputs": [
        {
          "internalType": "contract IUniswapV2Factory",
          "name": "",
          "type": "address"
        }
      ],
      "stateMutability": "view",
      "type": "function"
    },
    {
      "inputs": [],
      "name": "uniswapRouter",
      "outputs": [
        {
          "internalType": "contract IUniswapV2Router02",
          "name": "",
          "type": "address"
        }
      ],
      "stateMutability": "view",
      "type": "function"
    },
    {
      "stateMutability": "payable",
      "type": "receive"
    }
  ]
